{"frameRate":24,"name":"203","version":"5.5","compatibleVersion":"5.5","armature":[{"type":"Armature","frameRate":24,"name":"Armature","aabb":{"x":-98.5,"y":-108,"width":197,"height":214.99},"bone":[{"name":"root"},{"name":"bone_ikTarget2","parent":"root","transform":{"x":67.5573,"y":100.3019}},{"length":95,"name":"Layer_0","parent":"root","transform":{"x":31.45,"y":91.55,"skX":-93.6173,"skY":-93.6173}},{"name":"bone_ikTarget1","parent":"root","transform":{"x":-32.262,"y":102.5997}},{"name":"bone_ikTarget","parent":"root","transform":{"x":4.7106,"y":102.8295}},{"length":31,"name":"Layer_3","parent":"Layer_0","transform":{"x":11.274,"y":-81.6514,"skX":-92.6826,"skY":-92.6826}},{"length":21,"name":"Layer_5","parent":"Layer_0","transform":{"x":42.8834,"y":37.2799,"skX":97.8054,"skY":97.8054}},{"length":28,"name":"Layer_1","parent":"Layer_0","transform":{"x":23.4907,"y":-64.0956,"skX":-174.5865,"skY":-174.5865}},{"length":21,"name":"Layer_2_copy","parent":"Layer_0","transform":{"x":13.6839,"y":33.1795,"skX":176.8761,"skY":176.8761}},{"length":45,"name":"Layer_2","parent":"Layer_0","transform":{"x":41.4193,"y":-30.6979,"skX":176.6567,"skY":176.6567}},{"length":21,"name":"Layer_4","parent":"Layer_0","transform":{"x":42.7775,"y":6.4618,"skX":102.9907,"skY":102.9907}}],"slot":[{"name":"Layer_3","parent":"Layer_3"},{"name":"Layer_2_copy","parent":"Layer_2_copy"},{"name":"Layer_0","parent":"Layer_0"},{"name":"Layer_5","parent":"Layer_5"},{"name":"Layer_4","parent":"Layer_4"},{"name":"Layer_2","parent":"Layer_2"},{"name":"Layer_1","parent":"Layer_1"}],"ik":[{"name":"bone_ik1","bone":"Layer_1","target":"bone_ikTarget1"},{"name":"bone_ik2","bone":"Layer_2_copy","target":"bone_ikTarget2"},{"name":"bone_ik","bone":"Layer_2","target":"bone_ikTarget"}],"skin":[{"slot":[{"name":"Layer_3","display":[{"name":"203/Layer_3","transform":{"x":12.62,"y":1.85,"skX":-173.7,"skY":-173.7}}]},{"name":"Layer_1","display":[{"name":"203/Layer_1","transform":{"x":15.33,"y":-0.98,"skX":-91.8,"skY":-91.8}}]},{"name":"Layer_2","display":[{"name":"203/Layer_2","transform":{"x":23.83,"y":1.6,"skX":-83.04,"skY":-83.04}}]},{"name":"Layer_4","display":[{"name":"203/Layer_4","transform":{"x":9.41,"y":12.18,"skX":-9.37,"skY":-9.37}}]},{"name":"Layer_5","display":[{"name":"203/Layer_5","transform":{"x":9.91,"y":11.41,"skX":-4.19,"skY":-4.19}}]},{"name":"Layer_0","display":[{"name":"203/Layer_0","transform":{"x":94.56,"y":-13.01,"skX":93.62,"skY":93.62}}]},{"name":"Layer_2_copy","display":[{"name":"203/Layer_2_copy","transform":{"x":-3.16,"y":2.85,"skX":-83.26,"skY":-83.26}}]}]}],"animation":[{"duration":24,"playTimes":0,"name":"idle","bone":[{"name":"Layer_0","translateFrame":[{"duration":12,"tweenEasing":0},{"duration":12,"tweenEasing":0,"y":1.6},{"duration":0}]},{"name":"Layer_3","rotateFrame":[{"duration":12,"tweenEasing":0},{"duration":12,"tweenEasing":0,"rotate":10.95},{"duration":0}]},{"name":"Layer_1","translateFrame":[{"duration":12,"tweenEasing":0},{"duration":12,"tweenEasing":0,"x":2.51,"y":0.21},{"duration":0}],"rotateFrame":[{"duration":24,"rotate":-5.06}]},{"name":"Layer_2_copy","translateFrame":[{"duration":12,"tweenEasing":0},{"duration":12,"tweenEasing":0,"x":1.52,"y":0.11},{"duration":0}],"rotateFrame":[{"duration":24,"rotate":-2.21}]},{"name":"Layer_2","translateFrame":[{"duration":12,"tweenEasing":0},{"duration":12,"tweenEasing":0,"x":1.17,"y":0.07},{"duration":0}],"rotateFrame":[{"duration":24,"rotate":-0.36}]}]},{"duration":20,"playTimes":0,"name":"move","bone":[{"name":"bone_ikTarget2","translateFrame":[{"duration":10,"tweenEasing":0},{"duration":10,"tweenEasing":0,"x":-11.5,"y":-0.64},{"duration":0}]},{"name":"Layer_0","translateFrame":[{"duration":10,"tweenEasing":0},{"duration":10,"tweenEasing":0,"y":4.53},{"duration":0}]},{"name":"bone_ikTarget1","translateFrame":[{"duration":10,"tweenEasing":0},{"duration":10,"tweenEasing":0,"x":-12.6,"y":-1.58},{"duration":0}]},{"name":"bone_ikTarget","translateFrame":[{"duration":10,"tweenEasing":0},{"duration":10,"tweenEasing":0,"x":20.63,"y":-6.91},{"duration":0}]},{"name":"Layer_3","rotateFrame":[{"duration":16,"tweenEasing":0},{"duration":4,"tweenEasing":0,"rotate":15.7},{"duration":0}]},{"name":"Layer_5","rotateFrame":[{"duration":10,"tweenEasing":0},{"duration":6,"tweenEasing":0,"rotate":-24.29},{"duration":4,"tweenEasing":0,"rotate":-37.94},{"duration":0}]},{"name":"Layer_1","translateFrame":[{"duration":10,"tweenEasing":0},{"duration":10,"tweenEasing":0,"x":1.66,"y":-0.93},{"duration":0}],"rotateFrame":[{"duration":20,"rotate":-5.06}]},{"name":"Layer_2_copy","translateFrame":[{"duration":10,"tweenEasing":0},{"duration":10,"tweenEasing":0,"x":1.26,"y":-1.45},{"duration":0}],"rotateFrame":[{"duration":20,"rotate":-2.21}]},{"name":"Layer_2","rotateFrame":[{"duration":20,"rotate":-0.36}]},{"name":"Layer_4","rotateFrame":[{"duration":10,"tweenEasing":0},{"duration":6,"tweenEasing":0,"rotate":16.03},{"duration":4,"tweenEasing":0,"rotate":-11.13},{"duration":0}]}]},{"duration":25,"playTimes":0,"name":"attack","bone":[{"name":"Layer_0","translateFrame":[{"duration":8,"tweenEasing":0},{"duration":4,"tweenEasing":0,"x":-9.82,"y":-1.53},{"duration":13,"tweenEasing":0,"x":11.21,"y":0.05},{"duration":0}]},{"name":"Layer_3","rotateFrame":[{"duration":8,"tweenEasing":0},{"duration":17,"tweenEasing":0,"rotate":8.32},{"duration":0}]},{"name":"Layer_5","translateFrame":[{"duration":12,"tweenEasing":0},{"duration":13,"tweenEasing":0,"x":0.24,"y":5.86},{"duration":0}],"rotateFrame":[{"duration":8,"tweenEasing":0},{"duration":4,"tweenEasing":0,"rotate":21.31},{"duration":5,"tweenEasing":0,"rotate":-14.5},{"duration":8,"tweenEasing":0,"rotate":5.34},{"duration":0}]},{"name":"Layer_1","rotateFrame":[{"duration":25,"rotate":-5.06}]},{"name":"Layer_2_copy","rotateFrame":[{"duration":25,"rotate":-2.21}]},{"name":"Layer_2","rotateFrame":[{"duration":25,"rotate":-0.36}]},{"name":"Layer_4","translateFrame":[{"duration":12,"tweenEasing":0},{"duration":5,"tweenEasing":0,"x":0.3,"y":4.94},{"duration":8,"tweenEasing":0,"x":0.19,"y":3.04},{"duration":0}],"rotateFrame":[{"duration":8,"tweenEasing":0},{"duration":4,"tweenEasing":0,"rotate":-28.83},{"duration":5,"tweenEasing":0,"rotate":6.8},{"duration":8,"tweenEasing":0,"rotate":-23.71},{"duration":0}]}]},{"duration":24,"playTimes":0,"name":"die","bone":[{"name":"bone_ikTarget2","translateFrame":[{"duration":24,"tweenEasing":0},{"duration":0,"x":9.18,"y":-3.23}]},{"name":"Layer_0","translateFrame":[{"duration":24,"tweenEasing":0},{"duration":0,"x":-0.54,"y":18.86}]},{"name":"bone_ikTarget1","translateFrame":[{"duration":24,"tweenEasing":0},{"duration":0,"x":-34.49,"y":3.23}]},{"name":"bone_ikTarget","translateFrame":[{"duration":24,"tweenEasing":0},{"duration":0,"x":8.93,"y":-4.96}]},{"name":"Layer_3","rotateFrame":[{"duration":24,"tweenEasing":0},{"duration":0,"rotate":11.73}]},{"name":"Layer_5","rotateFrame":[{"duration":24,"tweenEasing":0,"rotate":-28.52},{"duration":0,"rotate":19.52}]},{"name":"Layer_1","rotateFrame":[{"duration":24,"rotate":-5.06}]},{"name":"Layer_2_copy","rotateFrame":[{"duration":24,"rotate":-2.21}]},{"name":"Layer_2","rotateFrame":[{"duration":24,"rotate":-0.36}]},{"name":"Layer_4","rotateFrame":[{"duration":24,"tweenEasing":0},{"duration":0,"rotate":37.18}]}]}],"defaultActions":[{"gotoAndPlay":"idle"}]}]}